{
  "rustsec_label": "Safe",
  "in_rustsec_patched": false,
  "in_rustsec_current": false,
  "in_rust_sec": false,
  "rustsec_tag": null,
  "developers": [
    "cart",
    "github:bevyengine:publish"
  ],
  "stars": 38567,
  "forks": 3794,
  "downloads": 141297,
  "num_side_effects": 6,
  "failed_rudra": false,
  "audits": [],
  "dependencies": [
    [
      "bevy_asset",
      "0.15.3"
    ],
    [
      "async-broadcast",
      "0.7.2"
    ],
    [
      "event-listener",
      "5.4.0"
    ],
    [
      "concurrent-queue",
      "2.5.0"
    ],
    [
      "crossbeam-utils",
      "0.8.21"
    ],
    [
      "pin-project-lite",
      "0.2.16"
    ],
    [
      "event-listener-strategy",
      "0.5.3"
    ],
    [
      "futures-core",
      "0.3.31"
    ],
    [
      "async-fs",
      "2.1.2"
    ],
    [
      "async-lock",
      "3.4.0"
    ],
    [
      "blocking",
      "1.6.1"
    ],
    [
      "async-channel",
      "2.3.1"
    ],
    [
      "async-task",
      "4.7.1"
    ],
    [
      "futures-io",
      "0.3.31"
    ],
    [
      "futures-lite",
      "2.6.0"
    ],
    [
      "piper",
      "0.2.4"
    ],
    [
      "atomic-waker",
      "1.1.2"
    ],
    [
      "fastrand",
      "2.3.0"
    ],
    [
      "atomicow",
      "1.1.0"
    ],
    [
      "portable-atomic",
      "1.11.0"
    ],
    [
      "portable-atomic-util",
      "0.2.4"
    ],
    [
      "bevy_app",
      "0.15.3"
    ],
    [
      "bevy_derive",
      "0.15.3"
    ],
    [
      "bevy_macro_utils",
      "0.15.3"
    ],
    [
      "proc-macro2",
      "1.0.94"
    ],
    [
      "unicode-ident",
      "1.0.18"
    ],
    [
      "quote",
      "1.0.40"
    ],
    [
      "syn",
      "2.0.100"
    ],
    [
      "toml_edit",
      "0.22.24"
    ],
    [
      "indexmap",
      "2.8.0"
    ],
    [
      "equivalent",
      "1.0.2"
    ],
    [
      "hashbrown",
      "0.15.2"
    ],
    [
      "toml_datetime",
      "0.6.8"
    ],
    [
      "bevy_ecs",
      "0.15.3"
    ],
    [
      "bevy_ecs_macros",
      "0.15.3"
    ],
    [
      "bevy_ptr",
      "0.15.3"
    ],
    [
      "bevy_tasks",
      "0.15.3"
    ],
    [
      "async-executor",
      "1.13.1"
    ],
    [
      "slab",
      "0.4.9"
    ],
    [
      "futures-channel",
      "0.3.31"
    ],
    [
      "pin-project",
      "1.1.10"
    ],
    [
      "pin-project-internal",
      "1.1.10"
    ],
    [
      "wasm-bindgen-futures",
      "0.4.50"
    ],
    [
      "cfg-if",
      "1.0.0"
    ],
    [
      "js-sys",
      "0.3.77"
    ],
    [
      "once_cell",
      "1.21.1"
    ],
    [
      "wasm-bindgen",
      "0.2.100"
    ],
    [
      "wasm-bindgen-macro",
      "0.2.100"
    ],
    [
      "wasm-bindgen-macro-support",
      "0.2.100"
    ],
    [
      "wasm-bindgen-backend",
      "0.2.100"
    ],
    [
      "bumpalo",
      "3.17.0"
    ],
    [
      "log",
      "0.4.26"
    ],
    [
      "wasm-bindgen-shared",
      "0.2.100"
    ],
    [
      "web-sys",
      "0.3.77"
    ],
    [
      "bevy_utils",
      "0.15.3"
    ],
    [
      "ahash",
      "0.8.11"
    ],
    [
      "zerocopy",
      "0.8.24"
    ],
    [
      "zerocopy-derive",
      "0.8.24"
    ],
    [
      "bevy_utils_proc_macros",
      "0.15.3"
    ],
    [
      "getrandom",
      "0.3.2"
    ],
    [
      "libc",
      "0.2.171"
    ],
    [
      "r-efi",
      "5.2.0"
    ],
    [
      "wasi",
      "0.7.0"
    ],
    [
      "tracing",
      "0.1.41"
    ],
    [
      "tracing-core",
      "0.1.33"
    ],
    [
      "web-time",
      "1.1.0"
    ],
    [
      "bitflags",
      "2.9.0"
    ],
    [
      "derive_more",
      "2.0.1"
    ],
    [
      "derive_more-impl",
      "2.0.1"
    ],
    [
      "disqualified",
      "1.0.0"
    ],
    [
      "fixedbitset",
      "0.5.7"
    ],
    [
      "nonmax",
      "0.5.5"
    ],
    [
      "petgraph",
      "0.7.1"
    ],
    [
      "smallvec",
      "1.14.0"
    ],
    [
      "console_error_panic_hook",
      "0.1.7"
    ],
    [
      "ctrlc",
      "3.4.5"
    ],
    [
      "nix",
      "0.29.0"
    ],
    [
      "windows-sys",
      "0.59.0"
    ],
    [
      "windows-targets",
      "0.53.0"
    ],
    [
      "windows_aarch64_gnullvm",
      "0.53.0"
    ],
    [
      "windows_aarch64_msvc",
      "0.53.0"
    ],
    [
      "windows_i686_gnu",
      "0.53.0"
    ],
    [
      "windows_i686_gnullvm",
      "0.53.0"
    ],
    [
      "windows_i686_msvc",
      "0.53.0"
    ],
    [
      "windows_x86_64_gnu",
      "0.53.0"
    ],
    [
      "windows_x86_64_gnullvm",
      "0.53.0"
    ],
    [
      "windows_x86_64_msvc",
      "0.53.0"
    ],
    [
      "downcast-rs",
      "2.0.1"
    ],
    [
      "bevy_asset_macros",
      "0.15.3"
    ],
    [
      "bevy_reflect",
      "0.15.3"
    ],
    [
      "assert_type_match",
      "0.1.1"
    ],
    [
      "bevy_reflect_derive",
      "0.15.3"
    ],
    [
      "uuid",
      "1.16.0"
    ],
    [
      "erased-serde",
      "0.4.6"
    ],
    [
      "serde",
      "1.0.219"
    ],
    [
      "serde_derive",
      "1.0.219"
    ],
    [
      "typeid",
      "1.0.3"
    ],
    [
      "bevy_window",
      "0.15.3"
    ],
    [
      "android-activity",
      "0.6.0"
    ],
    [
      "android-properties",
      "0.2.2"
    ],
    [
      "cesu8",
      "1.1.0"
    ],
    [
      "jni",
      "0.21.1"
    ],
    [
      "combine",
      "4.6.7"
    ],
    [
      "memchr",
      "2.7.4"
    ],
    [
      "jni-sys",
      "0.4.0"
    ],
    [
      "jni-sys-macros",
      "0.1.0"
    ],
    [
      "thiserror",
      "2.0.12"
    ],
    [
      "thiserror-impl",
      "2.0.12"
    ],
    [
      "ndk",
      "0.9.0"
    ],
    [
      "ndk-sys",
      "0.6.0+11769913"
    ],
    [
      "num_enum",
      "0.7.3"
    ],
    [
      "num_enum_derive",
      "0.7.3"
    ],
    [
      "ndk-context",
      "0.1.1"
    ],
    [
      "bevy_a11y",
      "0.15.3"
    ],
    [
      "accesskit",
      "0.18.0"
    ],
    [
      "bevy_input",
      "0.15.3"
    ],
    [
      "bevy_core",
      "0.15.3"
    ],
    [
      "bevy_math",
      "0.15.3"
    ],
    [
      "glam",
      "0.30.1"
    ],
    [
      "itertools",
      "0.14.0"
    ],
    [
      "either",
      "1.15.0"
    ],
    [
      "smol_str",
      "0.3.2"
    ],
    [
      "raw-window-handle",
      "0.6.2"
    ],
    [
      "blake3",
      "1.7.0"
    ],
    [
      "arrayref",
      "0.3.9"
    ],
    [
      "arrayvec",
      "0.7.6"
    ],
    [
      "constant_time_eq",
      "0.4.2"
    ],
    [
      "crossbeam-channel",
      "0.5.14"
    ],
    [
      "parking_lot",
      "0.12.3"
    ],
    [
      "lock_api",
      "0.4.12"
    ],
    [
      "scopeguard",
      "1.2.0"
    ],
    [
      "parking_lot_core",
      "0.9.10"
    ],
    [
      "redox_syscall",
      "0.5.10"
    ],
    [
      "ron",
      "0.9.0"
    ],
    [
      "base64",
      "0.22.1"
    ],
    [
      "stackfuture",
      "0.3.0"
    ],
    [
      "bevy_image",
      "0.15.3"
    ],
    [
      "bevy_color",
      "0.16.0"
    ],
    [
      "bevy",
      "0.15.3"
    ],
    [
      "bevy_internal",
      "0.15.3"
    ],
    [
      "bevy_diagnostic",
      "0.15.3"
    ],
    [
      "bevy_time",
      "0.15.3"
    ],
    [
      "const-fnv1a-hash",
      "1.1.0"
    ],
    [
      "bevy_hierarchy",
      "0.15.3"
    ],
    [
      "bevy_log",
      "0.15.3"
    ],
    [
      "android_log-sys",
      "0.3.2"
    ],
    [
      "tracing-log",
      "0.2.0"
    ],
    [
      "tracing-oslog",
      "0.2.0"
    ],
    [
      "tracing-subscriber",
      "0.3.19"
    ],
    [
      "tracing-wasm",
      "0.2.1"
    ],
    [
      "bevy_transform",
      "0.15.3"
    ],
    [
      "bytemuck",
      "1.22.0"
    ],
    [
      "image",
      "0.25.5"
    ],
    [
      "byteorder-lite",
      "0.1.0"
    ],
    [
      "num-traits",
      "0.2.19"
    ],
    [
      "wgpu",
      "24.0.3"
    ],
    [
      "document-features",
      "0.2.11"
    ],
    [
      "litrs",
      "0.4.1"
    ],
    [
      "profiling",
      "1.0.16"
    ],
    [
      "static_assertions",
      "1.1.0"
    ],
    [
      "wgpu-core",
      "24.0.2"
    ],
    [
      "bit-vec",
      "0.8.0"
    ],
    [
      "naga",
      "24.0.0"
    ],
    [
      "bit-set",
      "0.8.0"
    ],
    [
      "codespan-reporting",
      "0.11.1"
    ],
    [
      "termcolor",
      "1.4.1"
    ],
    [
      "winapi-util",
      "0.1.9"
    ],
    [
      "unicode-width",
      "0.2.0"
    ],
    [
      "rustc-hash",
      "2.1.1"
    ],
    [
      "strum",
      "0.27.1"
    ],
    [
      "wgpu-hal",
      "24.0.2"
    ],
    [
      "core-graphics-types",
      "0.2.0"
    ],
    [
      "core-foundation",
      "0.10.0"
    ],
    [
      "core-foundation-sys",
      "0.8.7"
    ],
    [
      "khronos-egl",
      "6.0.0"
    ],
    [
      "metal",
      "0.31.0"
    ],
    [
      "block",
      "0.1.6"
    ],
    [
      "foreign-types",
      "0.5.0"
    ],
    [
      "foreign-types-macros",
      "0.2.3"
    ],
    [
      "foreign-types-shared",
      "0.3.1"
    ],
    [
      "objc",
      "0.2.7"
    ],
    [
      "malloc_buf",
      "1.0.0"
    ],
    [
      "paste",
      "1.0.15"
    ],
    [
      "wgpu-types",
      "24.0.0"
    ],
    [
      "bevy_mikktspace",
      "0.15.3"
    ],
    [
      "hexasphere",
      "15.1.0"
    ],
    [
      "constgebra",
      "0.1.4"
    ],
    [
      "const_soft_float",
      "0.1.4"
    ]
  ],
  "passed_audit": false,
  "num_unsafe_calls": 0,
  "miri": false,
  "past_audit": false,
  "miri_details": {
    "status": "ok",
    "passed": 3,
    "failed": 0,
    "ignored": 0,
    "measured": 0,
    "filtered_out": 0,
    "time_seconds": 0.56
  }
}