{
  "rustsec_label": "Safe",
  "in_rustsec_patched": false,
  "in_rustsec_current": false,
  "in_rust_sec": false,
  "rustsec_tag": null,
  "developers": [
    "OptimisticPeach"
  ],
  "stars": 64,
  "forks": 15,
  "downloads": 3006877,
  "num_side_effects": 0,
  "failed_rudra": false,
  "audits": [],
  "dependencies": [
    [
      "constgebra",
      "0.1.4"
    ],
    [
      "const_soft_float",
      "0.1.4"
    ],
    [
      "glam",
      "0.30.1"
    ]
  ],
  "passed_audit": false,
  "num_unsafe_calls": 0,
  "miri": true,
  "past_audit": false,
  "miri_details": {
    "status": "timeout",
    "passed": 0,
    "failed": 0,
    "ignored": 0,
    "measured": 0,
    "filtered_out": 0,
    "time_seconds": 0.0
  }
}